{
  "_id": "d4549d25b111c71bae8b8932",
  "title": "Visual Identity Guidelines",
  "slug": "visual-identity-guidelines-easy-vision",
  "difficulty": "Easy",
  "topics": [
    "VISION"
  ],
  "scenario": "Create a set of visual identity guidelines for a new fashion brand. The target artifact is a short paragraph that outlines the brand's color palette, typography, and logo usage.",
  "targetArtifactType": "text",
  "constraints": [
    "Must be under 100 words",
    "Must use proper branding terminology like 'color scheme' and 'typography'"
  ],
  "evaluationCriteria": [
    {
      "id": "adherence_to_constraints",
      "description": "Check if the guidelines are under 100 words and use proper branding terminology.",
      "weight": 25
    },
    {
      "id": "tone_check",
      "description": "Evaluate the tone of the guidelines, ensuring they're professional and clear.",
      "weight": 25
    },
    {
      "id": "content_accuracy",
      "description": "Verify that the guidelines accurately outline the brand's color palette, typography, and logo usage.",
      "weight": 50
    }
  ],
  "judgeConfig": {
    "judgeModel": "llama-3.3-70b-versatile",
    "comparisonMode": "head_to_head"
  },
  "scoring": {
    "maxScore": 100
  },
  "battleConfig": {
    "enabled": true,
    "timeBonus": false,
    "maxBattleScore": 100
  },
  "tags": [
    "branding-guidelines",
    "visual-identity"
  ]
}