{
  "_id": "25fb28b60801129c556f78db",
  "title": "Generating a nested data structure from a prompt",
  "slug": "generating-a-nested-data-structure-from-a-prompt-hard-prompt-optimization",
  "difficulty": "Hard",
  "topics": [
    "PROMPT_OPTIMIZATION"
  ],
  "scenario": "Write a prompt that generates a nested data structure representing a company's organizational hierarchy. The structure should include 5 levels of hierarchy, with each level having a unique set of attributes. The prompt should use an informal tone and be under 200 words.",
  "targetArtifactType": "json",
  "constraints": [
    "Must use a nested structure to represent the hierarchy",
    "Must include attributes for each level of hierarchy",
    "Must be generated based on the prompt"
  ],
  "evaluationCriteria": [
    {
      "id": "nested_structure",
      "description": "Does the prompt accurately generate a nested data structure representing the organizational hierarchy?",
      "weight": 30
    },
    {
      "id": "attribute_inclusion",
      "description": "Does the prompt include attributes for each level of hierarchy?",
      "weight": 25
    },
    {
      "id": "generative_accuracy",
      "description": "Does the prompt accurately generate the data structure based on the prompt?",
      "weight": 20
    },
    {
      "id": "adherence_to_constraints",
      "description": "Does the prompt accurately implement the specified constraints?",
      "weight": 25
    }
  ],
  "judgeConfig": {
    "judgeModel": "llama-3.3-70b-versatile",
    "comparisonMode": "head_to_head"
  },
  "scoring": {
    "maxScore": 100
  },
  "battleConfig": {
    "enabled": true,
    "timeBonus": false,
    "maxBattleScore": 100
  },
  "tags": [
    "nested-data-structure",
    "organizational-hierarchy"
  ]
}