{
  "_id": "99f8f5f087cf6f86762207db",
  "title": "Stable Selection Sort with Incorrect Comparison",
  "slug": "stable-selection-sort-with-incorrect-comparison-bugfix-medium-sorting-1",
  "difficulty": "Medium",
  "category": "DSA",
  "subCategory": "SORTING",
  "mode": "bug_fix",
  "metadata": {
    "estimatedTime": 15,
    "points": 50,
    "premium": false,
    "isPublished": true,
    "companies": [],
    "topics": [
      "DSA"
    ],
    "patterns": [],
    "prerequisites": [],
    "variants": [],
    "tags": [
      "bug-fix",
      "medium"
    ],
    "keywords": [
      "bug-fix",
      "sorting"
    ],
    "interviewFrequency": 2,
    "revisionLevel": 0,
    "contestEligible": false
  },
  "statement": {
    "markdown": "Implement a stable selection sort algorithm to sort an array of integers in ascending order. The function should return the sorted array. Consider edge cases where the array is already sorted, empty, or contains duplicates.",
    "inputFormat": "An array of integers, e.g. [4, 2, 8, 3, 1]",
    "outputFormat": "The sorted array, e.g. [1, 2, 3, 4, 8]",
    "notes": "",
    "images": [],
    "constraints": [
      {
        "variable": "n",
        "type": "integer",
        "min": 0,
        "max": 10000,
        "description": "Size of array"
      }
    ],
    "examples": [
      {
        "input": "3\n1 2 3",
        "output": "0",
        "explanation": ""
      }
    ]
  },
  "hints": [
    {
      "order": 1,
      "text": "First hint text"
    }
  ],
  "editorial": {
    "title": "Editorial title",
    "intuition": "Explanation of the correct approach",
    "bruteForce": "Brute force approach summary",
    "betterSolution": "",
    "optimalSolution": "Optimal solution details",
    "proofOfCorrectness": "Correctness proof",
    "dryRun": "Step-by-step example run",
    "commonMistakes": [
      "Mistake 1",
      "Mistake 2"
    ],
    "timeComplexity": "O(n^2) ",
    "spaceComplexity": "O(1)"
  },
  "starterCode": {
    "cpp": "class Solution {\npublic:\n    std::vector<int> sortArray(std::vector<int>& nums);\n};",
    "java": "public class Solution {\npublic:\n    int[] sortArray(int[] nums);\n}",
    "python": "class Solution:\n    def sortArray(self, nums: list[int]) -> list[int]:\n\n        pass",
    "javascript": "function solve(nums) {\n        // TODO: implement\n\n}"
  },
  "buggyStarterCode": {
    "cpp": "class Solution {\npublic:\n    std::vector<int> sortArray(std::vector<int>& nums) {\n        for (int i = 0; i < nums.size(); i++) {\n            int minIndex = i;\n            for (int j = i + 1; j < nums.size(); j++) {\n                if (nums[minIndex] > nums[j]) {\n                    minIndex = j;\n                }\n            }\n\n            if (minIndex != i) {\n                std::swap(nums[i], nums[minIndex]);\n            }\n        }\n\n        return nums;\n    }\n};",
    "java": "public class Solution {\npublic int[] sortArray(int[] nums) {\n    for (int i = 0; i < nums.length; i++) {\n        int minIndex = i;\n        for (int j = i + 1; j < nums.length; j++) {\n            if (nums[minIndex] < nums[j]) {\n                minIndex = j;\n            }\n        }\n\n        if (minIndex != i) {\n            int temp = nums[i];\n            nums[i] = nums[minIndex];\n            nums[minIndex] = temp;\n        }\n    }\n\n    return nums;\n}}",
    "python": "class Solution:\n    def sortArray(self, nums: list[int]) -> list[int]:\n        for i in range(len(nums)):\n            minIndex = i\n            for j in range(i + 1, len(nums)):\n                if nums[minIndex] < nums[j]:\n                    minIndex = j\n\n            if minIndex != i:\n                nums[i], nums[minIndex] = nums[minIndex], nums[i]\n\n        return nums",
    "javascript": "function solve(nums) {\n    for (var i = 0; i < nums.length; i++) {\n        var minIndex = i;\n        for (var j = i + 1; j < nums.length; j++) {\n            if (nums[minIndex] < nums[j]) {\n                minIndex = j;\n            }\n        }\n\n        if (minIndex != i) {\n            var temp = nums[i];\n            nums[i] = nums[minIndex];\n            nums[minIndex] = temp;\n        }\n    }\n\n    return nums;\n}"
  },
  "functionSignature": {
    "cpp": "bool sortArray(std::vector<int>& nums);",
    "java": "public boolean sortArray(int[] nums);",
    "python": "def sortArray(self, nums: list[int]) -> bool:",
    "javascript": "var sortArray = function(nums);"
  },
  "solutions": {
    "python": "def main():\n    nums = [4, 2, 8, 3, 1]\n    sol = Solution()\n    res = sol.sortArray(nums)\n    print(res)\n\nif __name__ == '__main__':\n    main()",
    "cpp": "#include <iostream>\n#include <vector>\n\nusing namespace std;\n\nint main() {\n    vector<int> nums = {4, 2, 8, 3, 1};\n    Solution sol;\n    vector<int> res = sol.sortArray(nums);\n    for (int num : res) {\n        cout << num << ' ';\n    }\n    return 0;\n}",
    "java": "// Solution",
    "javascript": "// Solution"
  },
  "judgeConfig": {
    "timeLimit": 2,
    "memoryLimit": 256,
    "supportedLanguages": [
      "cpp",
      "java",
      "python",
      "javascript"
    ]
  },
  "scoring": {
    "type": "binary",
    "maxScore": 100,
    "partialScoring": false
  },
  "battleConfig": {
    "enabled": true,
    "ratingEnabled": true,
    "timeBonus": false,
    "maxBattleScore": 100,
    "difficultyMultiplier": 1
  },
  "testCases": [
    {
      "id": "sample_1",
      "input": "5\n1 2 8 3 1",
      "output": "0",
      "isVisible": true,
      "weight": 1,
      "category": "sample"
    },
    {
      "id": "tc_2",
      "input": "2\n4 2",
      "output": "0",
      "isVisible": false,
      "weight": 1,
      "category": "hidden"
    }
  ],
  "analytics": {
    "likes": 0,
    "dislikes": 0,
    "totalSubmissions": 0,
    "acceptedSubmissions": 0,
    "averageRuntime": 0,
    "averageMemory": 0
  },
  "similarProblems": [],
  "followUpQuestions": [],
  "isDeleted": false,
  "deletedAt": null
}