{
  "_id": "173eb1c75d9d6017a9d0e0c5",
  "title": "Batmicky",
  "slug": "66-batmicky",
  "difficulty": "Medium",
  "topics": [
    "HTML_CSS"
  ],
  "statement": {
    "markdown": "## CSSBattle Challenge: Recreate the Target Design\n\nYour objective is to recreate the target design mockup in pure HTML and CSS with the lowest character count possible.\n\n### 🎨 Color Palette\n* Recreate the target design shown in the reference image.\n\n### 📐 Target Design Mockup\nUse the visual mockup shown in the panel to guide your coordinate alignment and shape proportions.\n"
  },
  "constraints": [
    "Canvas size must be 400px x 300px",
    "Must match the target design mockup visually"
  ],
  "referenceAssets": [
    {
      "url": "https://cdn.sanity.io/images/r2p34icm/production/8184f91d91a2cb8d917e563f7b51f2a4259c5390-400x300.png",
      "caption": "Recreate target design: Batmicky"
    }
  ],
  "starterCode": {
    "html": "<div></div>",
    "css": "body {\n  background: #191919;\n}",
    "javascript": ""
  },
  "gradingCriteria": [
    {
      "id": "visual_correctness",
      "description": "Check that the rendered output matches the target design pixel-for-pixel.",
      "weight": 100
    }
  ],
  "judgeConfig": {
    "judgeModel": "meta-llama/llama-4-scout-17b-16e-instruct",
    "stack": [
      "html",
      "css"
    ],
    "referenceSolution": "<div id=\"bat\">\n  <div id=\"dark\">\n    <div id=\"head\">\n      <div id=\"ears\"></div>\n    </div>\n  </div>\n</div>\n<div id=\"wings\"></div>\n<style>\n  body {\n    background: #191919;\n    display: grid;\n    place-items: center;\n  }\n  #bat {\n    width: 240px;\n    height: 100px;\n    background: #F2AD43;\n  }\n  #wings {\n    position: absolute;\n    height: 100px;\n    width: 100px;\n    background: #191919;\n    border-radius: 50%;\n    translate: -125px;\n    box-shadow: 65px 111px 0px 51px #191919, 185px 111px 0px 51px #191919, 250px 0px #191919;\n  }\n  #bat, #dark {\n    display: grid;\n    justify-content: center;\n  }\n  #dark {\n    width: 80px;\n    height: 30px;\n    background: #191919;\n    border-radius: 0px 0px 10px 10px;\n    align-items: end;\n  }\n  #head {\n    width: 20px;\n    height: 20px;\n    background: #F2AD43;\n  }\n  #ears {\n    width: 10px;\n    height: 10px;\n    background: #F2AD43;\n    border-radius: 50%;\n    translate: -50% -50%;\n    box-shadow: 20px 0px #F2AD43;\n  }\n</style>"
  },
  "scoring": {
    "maxScore": 100,
    "passingScore": 70
  },
  "battleConfig": {
    "enabled": true,
    "timeBonus": false,
    "maxBattleScore": 100
  }
}