{
  "_id": "b042c629533a8c14930c2d29",
  "title": "Complex ASCII Diagram Generator",
  "slug": "complex-ascii-diagram-generator-hard-prompt-debugging",
  "difficulty": "Hard",
  "topics": [
    "PROMPT_DEBUGGING"
  ],
  "scenario": "Design a prompt that can generate a specific complex ASCII diagram involving multiple shapes, lines, and text. The prompt should be able to handle varying levels of complexity and provide clear explanations for each shape and line.",
  "targetArtifactType": "ui",
  "constraints": [
    "Must use a specific set of ASCII characters",
    "Must be under 80 characters wide"
  ],
  "evaluationCriteria": [
    {
      "id": "visual_accuracy",
      "description": "Does the generated diagram match the expected design?",
      "weight": 42
    },
    {
      "id": "clarity",
      "description": "How clear and easy to understand is the generated diagram?",
      "weight": 29
    },
    {
      "id": "reusability",
      "description": "How reusable is the generated prompt in handling different ASCII diagrams?",
      "weight": 29
    }
  ],
  "judgeConfig": {
    "judgeModel": "llama-3.3-70b-versatile",
    "comparisonMode": "head_to_head"
  },
  "scoring": {
    "maxScore": 100
  },
  "battleConfig": {
    "enabled": true,
    "timeBonus": false,
    "maxBattleScore": 100
  },
  "tags": [
    "ascii_diagrams",
    "prompt_debugging"
  ]
}