{
  "_id": "2ff67195b8a38fda963174cc",
  "title": "Conference Agenda Planner",
  "slug": "conference-agenda-planner-easy-planning",
  "difficulty": "Easy",
  "topics": [
    "PLANNING"
  ],
  "scenario": "Plan a simple conference agenda for a single day. The agenda should include 6 sessions. Each session should include the session title, speaker name, and start/end time. The agenda should be formatted as a table with clear column headers.",
  "targetArtifactType": "markdown",
  "constraints": [
    "Must be under 200 characters per row",
    "Must have 6 sessions"
  ],
  "evaluationCriteria": [
    {
      "id": "adherence_to_constraints",
      "description": "Check if the agenda meets the constraints of having 6 sessions and being under 200 characters per row.",
      "weight": 50
    },
    {
      "id": "formatting",
      "description": "Check if the agenda is formatted as a table with clear column headers.",
      "weight": 25
    },
    {
      "id": "correct_session_info",
      "description": "Check if each session includes the correct information (title, speaker name, start/end time).",
      "weight": 25
    }
  ],
  "judgeConfig": {
    "judgeModel": "llama-3.3-70b-versatile",
    "comparisonMode": "head_to_head"
  },
  "scoring": {
    "maxScore": 100
  },
  "battleConfig": {
    "enabled": true,
    "timeBonus": false,
    "maxBattleScore": 100
  },
  "tags": [
    "conference",
    "agenda"
  ]
}