{
  "_id": "69933ffab392da88b39f166a",
  "title": "Summarizing Technical Documents",
  "slug": "summarizing-technical-documents-medium-summarization",
  "difficulty": "Medium",
  "topics": [
    "SUMMARIZATION"
  ],
  "scenario": "Given a technical document of approximately 500 words, write a summary of no more than 150 words that captures the main points, including key technical terms and definitions.",
  "targetArtifactType": "markdown",
  "constraints": [
    "Must include key technical terms and definitions",
    "Summary should be no more than 150 words"
  ],
  "evaluationCriteria": [
    {
      "id": "adherence_to_constraints",
      "description": "Check if the summary meets the word count and structural requirements.",
      "weight": 30
    },
    {
      "id": "main_points_identification",
      "description": "Verify that the summary accurately captures the main points of the technical document.",
      "weight": 25
    },
    {
      "id": "technical_term_accuracy",
      "description": "Check if the technical terms mentioned in the summary match the ones provided in the document.",
      "weight": 20
    },
    {
      "id": "definition_provision",
      "description": "Ensure the summary accurately defines key technical terms and concepts.",
      "weight": 25
    }
  ],
  "judgeConfig": {
    "judgeModel": "llama-3.3-70b-versatile",
    "comparisonMode": "head_to_head"
  },
  "scoring": {
    "maxScore": 100
  },
  "battleConfig": {
    "enabled": true,
    "timeBonus": false,
    "maxBattleScore": 100
  },
  "tags": [
    "technical_summaries",
    "document_analysis"
  ]
}